{
  "changedFilesIos": [
    "res\\icons\\windows\\logo.png",
    "res\\icons\\android\\icon-72-hdpi.png",
    "res\\screens\\android\\screen-mdpi-landscape.png",
    "merges\\android\\scripts\\android2.3-jscompat.js",
    "res\\native\\windows\\CordovaApp_TemporaryKey.pfx",
    "merges\\windows\\scripts\\winstore-jscompat.js",
    "res\\icons\\ios\\icon-60.png",
    "res\\screens\\windows\\splashscreen.png",
    "res\\icons\\android\\icon-48-mdpi.png",
    "css\\index.css",
    "res\\icons\\ios\\icon-72.png",
    "res\\icons\\ios\\icon-76.png",
    "res\\icons\\windows\\storelogo.png",
    "res\\screens\\ios\\screen-ipad-portrait-2x.png",
    "res\\screens\\ios\\screen-iphone-portrait-2x.png",
    "res\\icons\\windows\\smalllogo.png",
    "res\\icons\\windows\\Square71x71Logo.scale-240.png",
    "merges\\android\\scripts\\platformOverrides.js",
    "res\\screens\\android\\screen-hdpi-portrait.png",
    "res\\icons\\windows\\StoreLogo.scale-240.png",
    "res\\screens\\ios\\screen-ipad-landscape.png",
    "scripts\\index.js",
    "config.xml",
    "res\\screens\\ios\\screen-ipad-landscape-2x.png",
    "res\\screens\\ios\\screen-iphone-568h-2x.png",
    "res\\screens\\wp8\\screen-portrait.jpg",
    "res\\screens\\android\\screen-ldpi-landscape.png",
    "res\\icons\\windows\\Wide310x150Logo.scale-240.png",
    "res\\icons\\ios\\icon-72-2x.png",
    "res\\icons\\ios\\icon-76-2x.png",
    "res\\icons\\ios\\icon-small.png",
    "res\\icons\\wp8\\icon-62-tile.png",
    "res\\icons\\wp8\\icon-173-tile.png",
    "res\\icons\\ios\\icon-40.png",
    "res\\icons\\ios\\icon-60-2x.png",
    "scripts\\platformOverrides.js",
    "res\\screens\\android\\screen-ldpi-portrait.png",
    "res\\native\\android\\ant.properties",
    "res\\icons\\windows\\Square150x150Logo.scale-240.png",
    "res\\icons\\android\\icon-36-ldpi.png",
    "merges\\windows\\scripts\\platformOverrides.js",
    "res\\screens\\ios\\screen-iphone-portrait.png",
    "res\\screens\\android\\screen-xhdpi-portrait.png",
    "res\\icons\\ios\\icon-50-2x.png",
    "res\\icons\\ios\\icon-57-2x.png",
    "res\\icons\\ios\\icon-50.png",
    "res\\icons\\ios\\icon-57.png",
    "res\\icons\\ios\\icon-small-2x.png",
    "res\\screens\\windows\\SplashScreen.scale-240.png",
    "res\\icons\\android\\icon-96-xhdpi.png",
    "index.html",
    "res\\icons\\ios\\icon-40-2x.png",
    "res\\screens\\android\\screen-hdpi-landscape.png",
    "res\\screens\\ios\\screen-ipad-portrait.png",
    "res\\screens\\android\\screen-xhdpi-landscape.png",
    "res\\icons\\windows\\Square44x44Logo.scale-240.png",
    "res\\screens\\android\\screen-mdpi-portrait.png",
    "css\\klinik.PNG",
    "css\\op.gif",
    "css\\Logo_IVF_Hartmann.svg.png",
    "css\\bild.jpg",
    "css\\full.jpg",
    "css\\home.PNG",
    "css\\ev.PNG",
    "scripts\\script.js",
    "scripts\\jquery-2.1.1.min.js",
    "scripts\\jquery-2.1.1.min.map",
    "scripts\\jquery-2.1.1.js",
    "packages.config",
    "scripts\\jquery-2.1.1.intellisense.js",
    "css\\alters.PNG",
    "css\\apo.PNG",
    "css\\arzt.PNG",
    "css\\indus.PNG",
    "css\\private.PNG",
    "html\\klinik.html",
    "css\\klinik.css",
    "scripts\\jquery.mobile-1.4.1.min.js",
    "css\\jquery.mobile-1.4.1.min.css"
  ],
  "deletedFilesIos": [
    "scripts\\jquery-2.1.0-vsdoc.js",
    "scripts\\jquery-2.1.0.intellisense.js",
    "scripts\\jquery-2.1.0.js",
    "scripts\\jquery-2.1.0.min.js",
    "scripts\\jquery-2.1.0.min.map",
    "scripts\\jquery-2.1.1-vsdoc.js",
    "html\\page.html",
    "css\\stylesheet.css",
    "css\\jquery.mobile-1.4.5.min.css",
    "scripts\\jquery.mobile-1.4.5.min.js"
  ],
  "addedPluginsIos": [],
  "deletedPluginsIos": [],
  "changedFiles": [],
  "deletedFiles": [],
  "addedPlugins": [],
  "deletedPlugins": []
}